waveforms/WaveformLexer.py
waveforms/WaveformListener.py
waveforms/WaveformParser.py
waveforms/__init__.py
waveforms/__main__.py
waveforms/_waveform.cp310-win_amd64.pyd
waveforms/_waveform.pyi
waveforms/_waveform.pyx
waveforms/distortion.py
waveforms/multy_drag.py
waveforms/utils.py
waveforms/version.py
waveforms/waveform.py
waveforms/waveform_parser.py
waveforms-2.2.2.dist-info/licenses/LICENSE
waveforms-2.2.2.dist-info/METADATA
waveforms-2.2.2.dist-info/WHEEL
waveforms-2.2.2.dist-info/entry_points.txt
waveforms-2.2.2.dist-info/top_level.txt
waveforms-2.2.2.dist-info/RECORD
