Metadata-Version: 2.4
Name: waveforms
Version: 2.2.2
Summary: Edit waveforms used in experiment
Author-email: feihoo87 <feihoo87@gmail.com>
Maintainer-email: feihoo87 <feihoo87@gmail.com>
License: MIT License
Project-URL: Homepage, https://github.com/feihoo87/waveforms
Project-URL: Bug Reports, https://github.com/feihoo87/waveforms/issues
Project-URL: Source, https://github.com/feihoo87/waveforms/
Keywords: signal,waveform,experiment,laboratory
Classifier: Development Status :: 3 - Alpha
Classifier: Intended Audience :: Developers
Classifier: Intended Audience :: Science/Research
Classifier: License :: OSI Approved :: MIT License
Classifier: Operating System :: Microsoft :: Windows
Classifier: Operating System :: POSIX :: Linux
Classifier: Operating System :: MacOS :: MacOS X
Classifier: Topic :: Scientific/Engineering :: Interface Engine/Protocol Translator
Classifier: Programming Language :: Python
Classifier: Programming Language :: Python :: 3.10
Classifier: Programming Language :: Python :: 3.11
Classifier: Programming Language :: Python :: 3.12
Requires-Python: >=3.10
License-File: LICENSE
Requires-Dist: click>=7.1.2
Requires-Dist: dill>=0.3.6
Requires-Dist: numpy>=1.13.3
Requires-Dist: antlr4-python3-runtime>=4.11.1
Requires-Dist: scipy>=1.0.0
Provides-Extra: full
Requires-Dist: msgpack>=1.0.5; extra == "full"
Provides-Extra: test
Requires-Dist: pytest>=7.4.0; extra == "test"
Requires-Dist: pytest-asyncio>=0.21.1; extra == "test"
Provides-Extra: docs
Requires-Dist: Sphinx; extra == "docs"
Requires-Dist: sphinxcontrib-napoleon; extra == "docs"
Requires-Dist: sphinxcontrib-zopeext; extra == "docs"
Dynamic: license-file
